dagster_composable_graphs/__init__.py
dagster_composable_graphs/compose.py
dagster_composable_graphs/jobs.py
dagster_composable_graphs/models.py
dagster_composable_graphs/util.py
dagster_composable_graphs-0.1.2.dist-info/LICENSE
dagster_composable_graphs-0.1.2.dist-info/METADATA
dagster_composable_graphs-0.1.2.dist-info/WHEEL
dagster_composable_graphs-0.1.2.dist-info/RECORD
