Metadata-Version: 2.1
Name: dagster-composable-graphs
Version: 0.1.2
Summary: Library to create Dagster jobs from YAML
Author: Francisco Garcia Florez
Author-email: francisco@truevoid.dev
Requires-Python: >=3.10,<3.13
Classifier: Programming Language :: Python :: 3
Classifier: Programming Language :: Python :: 3.10
Classifier: Programming Language :: Python :: 3.11
Classifier: Programming Language :: Python :: 3.12
Requires-Dist: dagster (>=1.7.4,<2.0.0)
Requires-Dist: jsonpointer (>=3.0.0,<4.0.0)
Requires-Dist: pydantic (>=2.7.1)
Requires-Dist: pyyaml (>=6.0.1,<7.0.0)
